pyjsbitwise/__init__.py
PyJsBitwise-1.0.2.dist-info/LICENSE
PyJsBitwise-1.0.2.dist-info/METADATA
PyJsBitwise-1.0.2.dist-info/WHEEL
PyJsBitwise-1.0.2.dist-info/top_level.txt
PyJsBitwise-1.0.2.dist-info/RECORD
