Metadata-Version: 2.1
Name: PyJsBitwise
Version: 1.0.2
Summary: JavaScript-flavored bitwise operations.
Home-page: https://github.com/Pairman/PyJsBitwise
Author: Pairman
Author-email: pairmanxlr@gmail.com
License: GNU General Public License v3 (GPLv3)
Project-URL: Homepage, https://github.com/Pairman/PyJsBitwise
Project-URL: Changelog, https://github.com/Pairman/PyJsBitwise/blob/main/CHANGELOG.md
Keywords: javascript,js,bitwise,shift
Classifier: Programming Language :: Python :: 3
Requires-Python: >= 3.0
License-File: LICENSE
